SigenAPI/__init__.py
SigenAPI/api.py
sigenapi-1.0.0.dist-info/METADATA
sigenapi-1.0.0.dist-info/WHEEL
sigenapi-1.0.0.dist-info/licenses/LICENSE
sigenapi-1.0.0.dist-info/RECORD
